README.txt
setup.py
collective/__init__.py
collective.portlets.reverseordering.egg-info/PKG-INFO
collective.portlets.reverseordering.egg-info/SOURCES.txt
collective.portlets.reverseordering.egg-info/dependency_links.txt
collective.portlets.reverseordering.egg-info/entry_points.txt
collective.portlets.reverseordering.egg-info/namespace_packages.txt
collective.portlets.reverseordering.egg-info/not-zip-safe
collective.portlets.reverseordering.egg-info/requires.txt
collective.portlets.reverseordering.egg-info/top_level.txt
collective/portlets/__init__.py
collective/portlets/reverseordering/__init__.py
collective/portlets/reverseordering/overrides.zcml
collective/portlets/reverseordering/retriever.py
docs/HISTORY.txt