Metadata-Version: 1.0
Name: collective.portlets.reverseordering
Version: 0.1
Summary: Reverse the acquisition ordering, having the global portlets on top and local at the bottom.
Home-page: UNKNOWN
Author: Helge Tesdal
Author-email: tesdal@jarn.com
License: LGPL
Keywords: plone
Platform: UNKNOWN
Classifier: Programming Language :: Python
Classifier: Topic :: Software Development :: Libraries :: Python Modules
